py_env_studio/__init__.py
py_env_studio/__main__.py
py_env_studio/config.ini
py_env_studio/main.py
py_env_studio/core/__init__.py
py_env_studio/core/configuration.py
py_env_studio/core/env_manager.py
py_env_studio/core/integration.py
py_env_studio/core/pip_tools.py
py_env_studio/core/strategies.py
py_env_studio/core/tools.py
py_env_studio/ui/__init__.py
py_env_studio/ui/main_window.py
py_env_studio/ui/static/icons/__init__.py
py_env_studio/ui/static/icons/about.png
py_env_studio/ui/static/icons/activate-env.png
py_env_studio/ui/static/icons/available-env.png
py_env_studio/ui/static/icons/create-env.png
py_env_studio/ui/static/icons/delete-env.png
py_env_studio/ui/static/icons/export.png
py_env_studio/ui/static/icons/install.png
py_env_studio/ui/static/icons/list-env.png
py_env_studio/ui/static/icons/logo.png
py_env_studio/ui/static/icons/packages.png
py_env_studio/ui/static/icons/pes-default-transparrent.png
py_env_studio/ui/static/icons/pes-icon-default.png
py_env_studio/ui/static/icons/requirements.png
py_env_studio/ui/static/icons/selected-env.png
py_env_studio/ui/static/icons/uninstall.png
py_env_studio/ui/static/icons/update.png
py_env_studio/utils/__init__.py
py_env_studio/utils/handlers.py
py_env_studio/utils/vulneribility_insights.py
py_env_studio/utils/vulneribility_scanner.py
py_env_studio-2.0.6.dist-info/licenses/LICENSE
py_env_studio-2.0.6.dist-info/METADATA
py_env_studio-2.0.6.dist-info/WHEEL
py_env_studio-2.0.6.dist-info/entry_points.txt
py_env_studio-2.0.6.dist-info/top_level.txt
py_env_studio-2.0.6.dist-info/RECORD
