Metadata-Version: 2.4
Name: py-env-studio
Version: 2.0.6
Summary: A cross-platform GUI and CLI tool for managing Python virtual environments and packages. Features include environment creation, activation, package installation, requirements management, updates, deletion, and export.
Author-email: Py Env Studio Team <contact.shaikh.wasim@gmail.com>
License: MIT License
Project-URL: Homepage, https://github.com/pyenvstudio/py-env-studio
Project-URL: Issues, https://github.com/pyenvstudio/py-env-studio/issues
Keywords: python,virtualenv,venv,conda,environment-manager,package-manager,dependency-manager,requirements.txt,pip,python-packages,python-gui,cli,virtual-environment-gui,pyenv,python-env,python-environment-manager,pip-gui,pip-manager,python-security,vulnerability-scanner,python-tool,cross-platform,IDE
Classifier: Development Status :: 5 - Production/Stable
Classifier: Intended Audience :: Developers
Classifier: Intended Audience :: System Administrators
Classifier: License :: OSI Approved :: MIT License
Classifier: Programming Language :: Python :: 3
Classifier: Programming Language :: Python :: 3.8
Classifier: Programming Language :: Python :: 3.9
Classifier: Programming Language :: Python :: 3.10
Classifier: Programming Language :: Python :: 3.11
Classifier: Programming Language :: Python :: 3.12
Classifier: Programming Language :: Python :: 3.13
Classifier: Operating System :: OS Independent
Classifier: Topic :: Software Development
Classifier: Topic :: Software Development :: Build Tools
Classifier: Topic :: Software Development :: Libraries :: Python Modules
Classifier: Topic :: System :: Installation/Setup
Classifier: Topic :: Utilities
Requires-Python: >=3.7
License-File: LICENSE
Requires-Dist: customtkinter>=5.2.2
Requires-Dist: Pillow>=11.3.0
Requires-Dist: matplotlib>=3.10.5
Requires-Dist: cvss>=3.6
Requires-Dist: Requests
Requires-Dist: pip
Requires-Dist: setuptools
Requires-Dist: wheel
Provides-Extra: dev
Requires-Dist: pytest; extra == "dev"
Requires-Dist: black; extra == "dev"
Requires-Dist: isort; extra == "dev"
Provides-Extra: gui
Requires-Dist: Pillow; extra == "gui"
Dynamic: license-file
